{
  "name": "Kinto",
  "description": "Kinto is a minimalist JSON storage service with synchronisation and sharing abilities.",
  "repository": {
    "url": "https://github.com/Kinto/kinto",
    "license": "Apache License (2.0)",
    "tests": "https://github.com/Kinto/kinto/actions"
  },
  "participate": {
    "home": "https://kinto.readthedocs.io/en/latest/community.html#how-to-contribute",
    "docs": "https://kinto.readthedocs.io/",
    "irc": "irc://irc.freenode.org/#kinto",
    "irc-contacts": ["alexis", "leplatrem", "magopian", "natim", "NiKo`"]
  },
  "bugs": {
    "list": "https://github.com/Kinto/kinto/issues",
    "report": "https://github.com/Kinto/kinto/issues/new"
  },
  "keywords": [
    "JSON",
    "Python",
    "Pyramid",
    "REST",
    "API",
    "Database"
  ]
}
